{"cand":[{"sqcand":"230001610953","n":"3312","nm":"CLAUDIONEI DO AGRO","cc":"PMN","st":"Não eleito","dvt":"Válido","vap":"823","pvap":"0,28"},{"sqcand":"230001610811","n":"5051","nm":"LUÍS OCA","cc":"PSOL - Federação PSOL REDE (PSOL/REDE)","st":"Não eleito","dvt":"Válido","vap":"52","pvap":"0,02"},{"sqcand":"230001611100","n":"5112","nm":"PASTORA JOELMA PAMPOLHA","cc":"PATRIOTA","st":"Não eleito","dvt":"Válido","vap":"25","pvap":"0,01"},{"sqcand":"230001600147","n":"5515","nm":"HIGOR ARAÚJO","cc":"PSD","st":"Suplente","dvt":"Válido","vap":"124","pvap":"0,04"},{"sqcand":"230001600155","n":"5522","nm":"YACHIN","cc":"PSD","st":"Suplente","dvt":"Válido","vap":"318","pvap":"0,11"},{"sqcand":"230001600153","n":"5599","nm":"PROFESSOR THIAGO REIS","cc":"PSD","st":"Suplente","dvt":"Válido","vap":"2186","pvap":"0,75"},{"sqcand":"230001643486","n":"7777","nm":"OTTACI","cc":"SOLIDARIEDADE","st":"Não eleito","dvt":"Anulado sub judice","vap":"209","pvap":"0,07"},{"sqcand":"230001600104","n":"9011","nm":"KIKA SAUDE","cc":"PROS","st":"Não eleito","dvt":"Válido","vap":"640","pvap":"0,22"},{"sqcand":"230001600100","n":"9033","nm":"MARIA DA FELICIDADE","cc":"PROS","st":"Não eleito","dvt":"Válido","vap":"321","pvap":"0,11"},{"sqcand":"230001600113","n":"1033","nm":"CIDA LACERDA","cc":"REPUBLICANOS","st":"Suplente","dvt":"Válido","vap":"1332","pvap":"0,46"},{"sqcand":"230001604228","n":"1144","nm":"DOUTOR JOEL","cc":"PP","st":"Não eleito","dvt":"Válido","vap":"1587","pvap":"0,54"},{"sqcand":"230001714012","n":"1201","nm":"PROFESSOR KLEBER","cc":"PDT","st":"Não eleito","dvt":"Válido","vap":"115","pvap":"0,04"},{"sqcand":"230001714010","n":"1234","nm":"FLÁVIO ZACHER","cc":"PDT","st":"Não eleito","dvt":"Válido","vap":"106","pvap":"0,04"},{"sqcand":"230001693303","n":"1400","nm":"SARGENTO BENEDITO","cc":"PTB","st":"Não eleito","dvt":"Válido","vap":"161","pvap":"0,06"},{"sqcand":"230001693302","n":"1445","nm":"TUXAUA LUPEDRO","cc":"PTB","st":"Não eleito","dvt":"Válido","vap":"74","pvap":"0,03"},{"sqcand":"230001602806","n":"1515","nm":"HELENA DA ASATUR","cc":"MDB","st":"Eleito por QP","dvt":"Válido","vap":"15848","pvap":"5,43"},{"sqcand":"230001602810","n":"1545","nm":"RONALDO TRAJANO","cc":"MDB","st":"Suplente","dvt":"Válido","vap":"1115","pvap":"0,38"},{"sqcand":"230001605869","n":"1977","nm":"SARGENTO PRISCILLA","cc":"PODE","st":"Não eleito","dvt":"Válido","vap":"1656","pvap":"0,57"},{"sqcand":"230001604290","n":"2222","nm":"RODRIGO CATARATAS","cc":"PL","st":"Não eleito","dvt":"Válido","vap":"9095","pvap":"3,11"},{"sqcand":"230001613691","n":"2711","nm":"KONCHITA","cc":"DC","st":"Não eleito","dvt":"Válido","vap":"62","pvap":"0,02"},{"sqcand":"230001602196","n":"2828","nm":"HAYDEE PARREIRA","cc":"PRTB","st":"Não eleito","dvt":"Válido","vap":"37","pvap":"0,01"},{"sqcand":"230001610810","n":"1818","nm":"JOENIA WAPICHANA","cc":"REDE - Federação PSOL REDE (PSOL/REDE)","st":"Não eleito","dvt":"Válido","vap":"11221","pvap":"3,84"},{"sqcand":"230001610806","n":"1813","nm":"PROFESSORA DRA ANTONIA COSTA","cc":"REDE - Federação PSOL REDE (PSOL/REDE)","st":"Não eleito","dvt":"Válido","vap":"405","pvap":"0,14"},{"sqcand":"230001600063","n":"2011","nm":"LUIZA TORQUATO","cc":"PSC","st":"Não eleito","dvt":"Válido","vap":"65","pvap":"0,02"},{"sqcand":"230001613696","n":"2777","nm":"ELY DE RORAIMA","cc":"DC","st":"Não eleito","dvt":"Válido","vap":"50","pvap":"0,02"},{"sqcand":"230001611099","n":"5120","nm":"PASTOR EDILBERTO PINTO","cc":"PATRIOTA","st":"Não eleito","dvt":"Válido","vap":"29","pvap":"0,01"},{"sqcand":"230001600151","n":"5500","nm":"SIMONE QUEIROZ","cc":"PSD","st":"Suplente","dvt":"Válido","vap":"8970","pvap":"3,07"},{"sqcand":"230001602812","n":"1522","nm":"NOÉLIA ALVES","cc":"MDB","st":"Suplente","dvt":"Válido","vap":"1703","pvap":"0,58"},{"sqcand":"230001610956","n":"3333","nm":"JACKSON FALCÃO","cc":"PMN","st":"Não eleito","dvt":"Válido","vap":"745","pvap":"0,26"},{"sqcand":"230001595284","n":"4477","nm":"JEFERSON ALVES","cc":"UNIÃO","st":"Suplente","dvt":"Válido","vap":"7111","pvap":"2,43"},{"sqcand":"230001611098","n":"5107","nm":"LACERDA","cc":"PATRIOTA","st":"Não eleito","dvt":"Válido","vap":"87","pvap":"0,03"},{"sqcand":"230001602813","n":"1533","nm":"DR. SAMIR XAUD","cc":"MDB","st":"Suplente","dvt":"Válido","vap":"4816","pvap":"1,65"},{"sqcand":"230001602807","n":"1556","nm":"REGIANE MATOS","cc":"MDB","st":"Suplente","dvt":"Válido","vap":"4338","pvap":"1,49"},{"sqcand":"230001600154","n":"5566","nm":"VICENTE NOGUEIRA","cc":"PSD","st":"Suplente","dvt":"Válido","vap":"23","pvap":"0,01"},{"sqcand":"230001600108","n":"1010","nm":"VITOR VICENTE","cc":"REPUBLICANOS","st":"Suplente","dvt":"Válido","vap":"4833","pvap":"1,65"},{"sqcand":"230001600106","n":"1000","nm":"GABRIEL MOTA","cc":"REPUBLICANOS","st":"Suplente","dvt":"Válido","vap":"6520","pvap":"2,23"},{"sqcand":"230001600149","n":"5555","nm":"ZÉ HAROLDO CATHEDRAL","cc":"PSD","st":"Eleito por média","dvt":"Válido","vap":"10361","pvap":"3,55"},{"sqcand":"230001610863","n":"4300","nm":"JOSY ENFERMEIRA","cc":"PV - Federação Brasil da Esperança - FE BRASIL (PT/PC do B/PV)","st":"Não eleito","dvt":"Válido","vap":"229","pvap":"0,08"},{"sqcand":"230001610955","n":"3388","nm":"STELLA BROSSI","cc":"PMN","st":"Não eleito","dvt":"Válido","vap":"83","pvap":"0,03"},{"sqcand":"230001604283","n":"2277","nm":"MAJ ADRIANE","cc":"PL","st":"Não eleito","dvt":"Válido","vap":"2760","pvap":"0,94"},{"sqcand":"230001611104","n":"5125","nm":"KIARA SILVA","cc":"PATRIOTA","st":"Não eleito","dvt":"Válido","vap":"4","pvap":"0,00"},{"sqcand":"230001595281","n":"4444","nm":"NICOLETTI","cc":"UNIÃO","st":"Eleito por QP","dvt":"Válido","vap":"10969","pvap":"3,76"},{"sqcand":"230001613692","n":"2710","nm":"MARIA DA SILVA","cc":"DC","st":"Não eleito","dvt":"Válido","vap":"33","pvap":"0,01"},{"sqcand":"230001600148","n":"5511","nm":"DRA ANA LUCIOLA","cc":"PSD","st":"Suplente","dvt":"Válido","vap":"1595","pvap":"0,55"},{"sqcand":"230001610807","n":"1888","nm":"PROFESSOR CÍRIO RICARDO","cc":"REDE - Federação PSOL REDE (PSOL/REDE)","st":"Não eleito","dvt":"Válido","vap":"684","pvap":"0,23"},{"sqcand":"230001714014","n":"1210","nm":"ROGERIO MIRANDA","cc":"PDT","st":"Não eleito","dvt":"Válido","vap":"70","pvap":"0,02"},{"sqcand":"230001640625","n":"2333","nm":"ISNEIDE NUNES","cc":"CIDADANIA - Federação PSDB Cidadania (PSDB/CIDADANIA)","st":"Não eleito","dvt":"Válido","vap":"82","pvap":"0,03"},{"sqcand":"230001605873","n":"1900","nm":"FABY ALBUQUERQUE","cc":"PODE","st":"Não eleito","dvt":"Válido","vap":"103","pvap":"0,04"},{"sqcand":"230001600119","n":"3599","nm":"CELINHA","cc":"PMB","st":"Não eleito","dvt":"Válido","vap":"118","pvap":"0,04"},{"sqcand":"230001643487","n":"7707","nm":"ALINE PEIXOTO","cc":"SOLIDARIEDADE","st":"Não eleito","dvt":"Válido","vap":"84","pvap":"0,03"},{"sqcand":"230001693307","n":"1441","nm":"WELLINGTON BRASIL","cc":"PTB","st":"Não eleito","dvt":"Válido","vap":"19","pvap":"0,01"},{"sqcand":"230001605872","n":"1922","nm":"JOSIAS LICATA","cc":"PODE","st":"Não eleito","dvt":"Válido","vap":"351","pvap":"0,12"},{"sqcand":"230001640627","n":"2300","nm":"KATIANE ALVES","cc":"CIDADANIA - Federação PSDB Cidadania (PSDB/CIDADANIA)","st":"Não eleito","dvt":"Válido","vap":"46","pvap":"0,02"},{"sqcand":"230001600112","n":"1077","nm":"DEFENSOR STÉLIO DENER","cc":"REPUBLICANOS","st":"Eleito por média","dvt":"Válido","vap":"14193","pvap":"4,86"},{"sqcand":"230001600110","n":"1012","nm":"PROF KELY","cc":"REPUBLICANOS","st":"Suplente","dvt":"Válido","vap":"1979","pvap":"0,68"},{"sqcand":"230001714011","n":"1240","nm":"JAM ENGENHARIA","cc":"PDT","st":"Não eleito","dvt":"Válido","vap":"27","pvap":"0,01"},{"sqcand":"230001604227","n":"1155","nm":"PROFESSOR ADEJALMO","cc":"PP","st":"Não eleito","dvt":"Válido","vap":"906","pvap":"0,31"},{"sqcand":"230001693306","n":"1425","nm":"EVANDRO MOREIRA","cc":"PTB","st":"Não eleito","dvt":"Válido","vap":"15","pvap":"0,01"},{"sqcand":"230001600065","n":"2022","nm":"MARÃO","cc":"PSC","st":"Não eleito","dvt":"Válido","vap":"146","pvap":"0,05"},{"sqcand":"230001605871","n":"1911","nm":"LUCIANO CASTRO","cc":"PODE","st":"Não eleito","dvt":"Válido","vap":"5157","pvap":"1,77"},{"sqcand":"230001600101","n":"9022","nm":"VANDERLEI","cc":"PROS","st":"Não eleito","dvt":"Válido","vap":"333","pvap":"0,11"},{"sqcand":"230001610809","n":"1823","nm":"HENRIQUE MATOS","cc":"REDE - Federação PSOL REDE (PSOL/REDE)","st":"Não eleito","dvt":"Válido","vap":"130","pvap":"0,04"},{"sqcand":"230001604226","n":"1100","nm":"DELEGADO FRANCISCO","cc":"PP","st":"Não eleito","dvt":"Válido","vap":"7629","pvap":"2,61"},{"sqcand":"230001693305","n":"1422","nm":"SAIONARA RODRIGUES","cc":"PTB","st":"Não eleito","dvt":"Válido","vap":"440","pvap":"0,15"},{"sqcand":"230001600118","n":"3500","nm":"MARCIANO","cc":"PMB","st":"Não eleito","dvt":"Válido","vap":"611","pvap":"0,21"},{"sqcand":"230001600116","n":"3522","nm":"JHONATAN CALEL","cc":"PMB","st":"Não eleito","dvt":"Válido","vap":"221","pvap":"0,08"},{"sqcand":"230001604231","n":"1190","nm":"MAJOR OVERLAN","cc":"PP","st":"Não eleito","dvt":"Válido","vap":"1555","pvap":"0,53"},{"sqcand":"230001604285","n":"2215","nm":"GLEYCE MOTA","cc":"PL","st":"Não eleito","dvt":"Válido","vap":"1756","pvap":"0,60"},{"sqcand":"230001610860","n":"1313","nm":"PROFESSORA ANTONIA PEDROSA","cc":"PT - Federação Brasil da Esperança - FE BRASIL (PT/PC do B/PV)","st":"Não eleito","dvt":"Válido","vap":"1920","pvap":"0,66"},{"sqcand":"230001600150","n":"5595","nm":"LINOBERG","cc":"PSD","st":"Suplente","dvt":"Válido","vap":"5635","pvap":"1,93"},{"sqcand":"230001600107","n":"1034","nm":"PROF IRISNAIDE MACUXI","cc":"REPUBLICANOS","st":"Suplente","dvt":"Válido","vap":"1514","pvap":"0,52"},{"sqcand":"230001722374","n":"2929","nm":"LIDIA PEREIRA","cc":"PCO","st":"Não eleito","dvt":"Anulado sub judice","vap":"5","pvap":"0,00"},{"sqcand":"230001737207","n":"4343","nm":"MARCOS ALMEIDA","cc":"PV - Federação Brasil da Esperança - FE BRASIL (PT/PC do B/PV)","st":"Não eleito","dvt":"Válido","vap":"3","pvap":"0,00"},{"sqcand":"230001602814","n":"1555","nm":"PAULINHO LINHARES","cc":"MDB","st":"Suplente","dvt":"Válido","vap":"1891","pvap":"0,65"},{"sqcand":"230001610804","n":"5055","nm":"JÚNIOR PARICARANA","cc":"PSOL - Federação PSOL REDE (PSOL/REDE)","st":"Não eleito","dvt":"Válido","vap":"145","pvap":"0,05"},{"sqcand":"230001605868","n":"1940","nm":"LUANA KARMINY","cc":"PODE","st":"Não eleito","dvt":"Válido","vap":"125","pvap":"0,04"},{"sqcand":"230001600111","n":"1011","nm":"JHONATAN DE JESUS","cc":"REPUBLICANOS","st":"Eleito por QP","dvt":"Válido","vap":"19881","pvap":"6,81"},{"sqcand":"230001595286","n":"4422","nm":"PASTORA EDNA","cc":"UNIÃO","st":"Suplente","dvt":"Válido","vap":"6319","pvap":"2,16"},{"sqcand":"230001610808","n":"5050","nm":"EUNICE MOREIRA","cc":"PSOL - Federação PSOL REDE (PSOL/REDE)","st":"Não eleito","dvt":"Válido","vap":"412","pvap":"0,14"},{"sqcand":"230001604289","n":"2200","nm":"EDIO JUNIOR","cc":"PL","st":"Não eleito","dvt":"Válido","vap":"10563","pvap":"3,62"},{"sqcand":"230001693308","n":"1444","nm":"GELB PEREIRA","cc":"PTB","st":"Não eleito","dvt":"Válido","vap":"194","pvap":"0,07"},{"sqcand":"230001605870","n":"1999","nm":"RAUL LIMA","cc":"PODE","st":"Não eleito","dvt":"Válido","vap":"6714","pvap":"2,30"},{"sqcand":"230001726099","n":"7755","nm":"IONE BRASIL","cc":"SOLIDARIEDADE","st":"Não eleito","dvt":"Válido","vap":"274","pvap":"0,09"},{"sqcand":"230001605874","n":"1933","nm":"PASTOR DEUSAILTON","cc":"PODE","st":"Não eleito","dvt":"Válido","vap":"1253","pvap":"0,43"},{"sqcand":"230001604229","n":"1107","nm":"JOICY VANIA","cc":"PP","st":"Não eleito","dvt":"Válido","vap":"93","pvap":"0,03"},{"sqcand":"230001600117","n":"3535","nm":"LEONILDE LIMA","cc":"PMB","st":"Não eleito","dvt":"Válido","vap":"271","pvap":"0,09"},{"sqcand":"230001610952","n":"3322","nm":"SHAOLYN","cc":"PMN","st":"Não eleito","dvt":"Válido","vap":"372","pvap":"0,13"},{"sqcand":"230001600096","n":"9090","nm":"EVERALDO FEDERAL","cc":"PROS","st":"Não eleito","dvt":"Válido","vap":"964","pvap":"0,33"},{"sqcand":"230001643492","n":"7744","nm":"KLEBER SIQUEIRA","cc":"SOLIDARIEDADE","st":"Não eleito","dvt":"Válido","vap":"126","pvap":"0,04"},{"sqcand":"230001604284","n":"2211","nm":"LOURDINHA PINHEIRO","cc":"PL","st":"Não eleito","dvt":"Válido","vap":"1186","pvap":"0,41"},{"sqcand":"230001610957","n":"3338","nm":"FILIPE BARCELOS","cc":"PMN","st":"Não eleito","dvt":"Válido","vap":"890","pvap":"0,30"},{"sqcand":"230001693309","n":"1477","nm":"KASSIA MOURA","cc":"PTB","st":"Não eleito","dvt":"Válido","vap":"167","pvap":"0,06"},{"sqcand":"230001604230","n":"1111","nm":"LURENE","cc":"PP","st":"Não eleito","dvt":"Válido","vap":"2168","pvap":"0,74"},{"sqcand":"230001640626","n":"2323","nm":"ZÉ RODRIGUES","cc":"CIDADANIA - Federação PSDB Cidadania (PSDB/CIDADANIA)","st":"Não eleito","dvt":"Válido","vap":"252","pvap":"0,09"},{"sqcand":"230001604233","n":"1177","nm":"MISSIONARIA MARTA","cc":"PP","st":"Não eleito","dvt":"Válido","vap":"453","pvap":"0,16"},{"sqcand":"230001643490","n":"7711","nm":"VICTOR DA VIP CELULAR","cc":"SOLIDARIEDADE","st":"Não eleito","dvt":"Válido","vap":"522","pvap":"0,18"},{"sqcand":"230001610805","n":"1880","nm":"YANO RODRIGUES","cc":"REDE - Federação PSOL REDE (PSOL/REDE)","st":"Não eleito","dvt":"Válido","vap":"455","pvap":"0,16"},{"sqcand":"230001600109","n":"1022","nm":"ALUIZIO NASCIMENTO","cc":"REPUBLICANOS","st":"Suplente","dvt":"Válido","vap":"2948","pvap":"1,01"},{"sqcand":"230001600098","n":"9001","nm":"PETITA BRASIL","cc":"PROS","st":"Não eleito","dvt":"Válido","vap":"230","pvap":"0,08"},{"sqcand":"230001602189","n":"2800","nm":"BAIXINHO DO GRÊMIO","cc":"PRTB","st":"Não eleito","dvt":"Válido","vap":"134","pvap":"0,05"},{"sqcand":"230001600114","n":"1099","nm":"ALBUQUERQUE","cc":"REPUBLICANOS","st":"Eleito por média","dvt":"Válido","vap":"14015","pvap":"4,80"},{"sqcand":"230001611097","n":"5123","nm":"AVENIR ROSA","cc":"PATRIOTA","st":"Não eleito","dvt":"Válido","vap":"27","pvap":"0,01"},{"sqcand":"230001595283","n":"4420","nm":"PASTOR DINIZ","cc":"UNIÃO","st":"Eleito por média","dvt":"Válido","vap":"8243","pvap":"2,82"},{"sqcand":"230001605875","n":"1919","nm":"PROFESSOR ERIK","cc":"PODE","st":"Não eleito","dvt":"Válido","vap":"532","pvap":"0,18"},{"sqcand":"230001728502","n":"5588","nm":"TEIA MOTA","cc":"PSD","st":"Suplente","dvt":"Válido","vap":"481","pvap":"0,16"},{"sqcand":"230001600064","n":"2020","nm":"DEAN FABRICIO","cc":"PSC","st":"Não eleito","dvt":"Válido","vap":"76","pvap":"0,03"},{"sqcand":"230001726100","n":"7790","nm":"JEREMIAS LIMA","cc":"SOLIDARIEDADE","st":"Não eleito","dvt":"Válido","vap":"12","pvap":"0,00"},{"sqcand":"230001595280","n":"4490","nm":"JOSEANE SOUZA","cc":"UNIÃO","st":"Suplente","dvt":"Válido","vap":"1584","pvap":"0,54"},{"sqcand":"230001611096","n":"5151","nm":"REIJANE CARVALHO","cc":"PATRIOTA","st":"Não eleito","dvt":"Válido","vap":"370","pvap":"0,13"},{"sqcand":"230001604232","n":"1114","nm":"ANGELA PORTELA","cc":"PP","st":"Não eleito","dvt":"Válido","vap":"6760","pvap":"2,31"},{"sqcand":"230001600097","n":"9093","nm":"RADIALISTA JANES MIRANDA","cc":"PROS","st":"Não eleito","dvt":"Válido","vap":"1071","pvap":"0,37"},{"sqcand":"230001693310","n":"1414","nm":"JACKELINE OLIVEIRA","cc":"PTB","st":"Não eleito","dvt":"Válido","vap":"59","pvap":"0,02"},{"sqcand":"230001726098","n":"1200","nm":"FRANCISCO FARIAS","cc":"PDT","st":"Não eleito","dvt":"Válido","vap":"101","pvap":"0,03"},{"sqcand":"230001714013","n":"1212","nm":"NARA BORRACHEIRA","cc":"PDT","st":"Não eleito","dvt":"Válido","vap":"341","pvap":"0,12"},{"sqcand":"230001610954","n":"3311","nm":"SAMARA MAGALHÃES","cc":"PMN","st":"Não eleito","dvt":"Válido","vap":"133","pvap":"0,05"},{"sqcand":"230001714015","n":"1229","nm":"THALITA GONZAGA","cc":"PDT","st":"Não eleito","dvt":"Anulado sub judice","vap":"41","pvap":"0,01"},{"sqcand":"230001604234","n":"1122","nm":"DEILSON BOLSONARO","cc":"PP","st":"Não eleito","dvt":"Válido","vap":"3264","pvap":"1,12"},{"sqcand":"230001595282","n":"4433","nm":"DOUTORA LIDIANE","cc":"UNIÃO","st":"Suplente","dvt":"Válido","vap":"950","pvap":"0,33"},{"sqcand":"230001640628","n":"4545","nm":"LUIZINHO DO HOSPITAL","cc":"PSDB - Federação PSDB Cidadania (PSDB/CIDADANIA)","st":"Não eleito","dvt":"Anulado sub judice","vap":"196","pvap":"0,07"},{"sqcand":"230001604287","n":"2223","nm":"JONAS MARCOLINO","cc":"PL","st":"Não eleito","dvt":"Válido","vap":"916","pvap":"0,31"},{"sqcand":"230001640624","n":"2310","nm":"SANTIAGO","cc":"CIDADANIA - Federação PSDB Cidadania (PSDB/CIDADANIA)","st":"Não eleito","dvt":"Válido","vap":"74","pvap":"0,03"},{"sqcand":"230001643488","n":"7700","nm":"DILA SANTOS","cc":"SOLIDARIEDADE","st":"Não eleito","dvt":"Válido","vap":"28","pvap":"0,01"},{"sqcand":"230001604288","n":"2244","nm":"WILLIAN OLIVEIRA","cc":"PL","st":"Não eleito","dvt":"Válido","vap":"289","pvap":"0,10"},{"sqcand":"230001600102","n":"9099","nm":"PASTOR ANTONIO EMILIANO","cc":"PROS","st":"Não eleito","dvt":"Válido","vap":"296","pvap":"0,10"},{"sqcand":"230001613695","n":"2727","nm":"MARLENE LOPES","cc":"DC","st":"Não eleito","dvt":"Válido","vap":"68","pvap":"0,02"},{"sqcand":"230001602190","n":"2814","nm":"GLEISSON MORAIS","cc":"PRTB","st":"Não eleito","dvt":"Válido","vap":"88","pvap":"0,03"},{"sqcand":"230001602193","n":"2808","nm":"VIVI ROCHA","cc":"PRTB","st":"Não eleito","dvt":"Válido","vap":"24","pvap":"0,01"},{"sqcand":"230001611102","n":"5100","nm":"NATO","cc":"PATRIOTA","st":"Não eleito","dvt":"Válido","vap":"128","pvap":"0,04"},{"sqcand":"230001595279","n":"4411","nm":"DELEGADO HERBERT","cc":"UNIÃO","st":"Suplente","dvt":"Válido","vap":"3158","pvap":"1,08"},{"sqcand":"230001602194","n":"2829","nm":"NEGÃO FORTE SOM","cc":"PRTB","st":"Não eleito","dvt":"Válido","vap":"38","pvap":"0,01"},{"sqcand":"230001640623","n":"4523","nm":"THALIA RIBEIRO","cc":"PSDB - Federação PSDB Cidadania (PSDB/CIDADANIA)","st":"Não eleito","dvt":"Válido","vap":"39","pvap":"0,01"},{"sqcand":"230001595285","n":"4455","nm":"THIAGO RODRIGUES","cc":"UNIÃO","st":"Suplente","dvt":"Válido","vap":"3129","pvap":"1,07"},{"sqcand":"230001602195","n":"2844","nm":"SARA LOPES","cc":"PRTB","st":"Não eleito","dvt":"Válido","vap":"65","pvap":"0,02"},{"sqcand":"230001640622","n":"2311","nm":"ZÉ SILVA","cc":"CIDADANIA - Federação PSDB Cidadania (PSDB/CIDADANIA)","st":"Não eleito","dvt":"Válido","vap":"60","pvap":"0,02"},{"sqcand":"230001610867","n":"4320","nm":"DRA ROSELI RIBEIRO","cc":"PV - Federação Brasil da Esperança - FE BRASIL (PT/PC do B/PV)","st":"Não eleito","dvt":"Válido","vap":"306","pvap":"0,10"},{"sqcand":"230001613694","n":"2722","nm":"CARLOS KOELHO","cc":"DC","st":"Não eleito","dvt":"Válido","vap":"229","pvap":"0,08"},{"sqcand":"230001693304","n":"1411","nm":"ORIB ZIEDSON","cc":"PTB","st":"Não eleito","dvt":"Válido","vap":"97","pvap":"0,03"},{"sqcand":"230001610866","n":"1323","nm":"ROMULO VACA","cc":"PT - Federação Brasil da Esperança - FE BRASIL (PT/PC do B/PV)","st":"Não eleito","dvt":"Anulado sub judice","vap":"25","pvap":"0,01"},{"sqcand":"230001600103","n":"9000","nm":"DR RAMON FELIPE","cc":"PROS","st":"Não eleito","dvt":"Válido","vap":"507","pvap":"0,17"},{"sqcand":"230001602811","n":"1500","nm":"DR. FRUTUOSO LINS","cc":"MDB","st":"Suplente","dvt":"Válido","vap":"3913","pvap":"1,34"},{"sqcand":"230001613693","n":"2700","nm":"DENIS ALCANTARA","cc":"DC","st":"Não eleito","dvt":"Válido","vap":"247","pvap":"0,08"},{"sqcand":"230001602809","n":"1510","nm":"DUDA RAMOS","cc":"MDB","st":"Eleito por média","dvt":"Válido","vap":"14793","pvap":"5,06"},{"sqcand":"230001714009","n":"1221","nm":"ANGELA CARVALHO","cc":"PDT","st":"Não eleito","dvt":"Válido","vap":"89","pvap":"0,03"},{"sqcand":"230001604291","n":"2299","nm":"TALITA CANAL","cc":"PL","st":"Não eleito","dvt":"Válido","vap":"11","pvap":"0,00"},{"sqcand":"230001640621","n":"2307","nm":"FÁBIO VIEIRA","cc":"CIDADANIA - Federação PSDB Cidadania (PSDB/CIDADANIA)","st":"Não eleito","dvt":"Válido","vap":"135","pvap":"0,05"},{"sqcand":"230001602188","n":"2822","nm":"MARRETA","cc":"PRTB","st":"Não eleito","dvt":"Válido","vap":"62","pvap":"0,02"},{"sqcand":"230001610868","n":"1310","nm":"PROF SIVALDO","cc":"PT - Federação Brasil da Esperança - FE BRASIL (PT/PC do B/PV)","st":"Não eleito","dvt":"Válido","vap":"279","pvap":"0,10"}]}