{"cand":[{"sqcand":"150001619546","n":"1017","nm":"IARA CAETANO","cc":"REPUBLICANOS","st":"Suplente","dvt":"Válido","vap":"3438","pvap":"0,16"},{"sqcand":"150001612075","n":"1133","nm":"ERINALDA MONTEIRO","cc":"PP","st":"Suplente","dvt":"Válido","vap":"1059","pvap":"0,05"},{"sqcand":"150001718129","n":"1251","nm":"IGOR CASABLANCAS","cc":"PDT","st":"Não eleito","dvt":"Válido","vap":"346","pvap":"0,02"},{"sqcand":"150001619540","n":"1311","nm":"LENILDO MORAIS","cc":"PT - Federação Brasil da Esperança - FE BRASIL (PT/PC do B/PV)","st":"Suplente","dvt":"Válido","vap":"7234","pvap":"0,33"},{"sqcand":"150001619539","n":"1345","nm":"FREI ANASTÁCIO","cc":"PT - Federação Brasil da Esperança - FE BRASIL (PT/PC do B/PV)","st":"Suplente","dvt":"Válido","vap":"39598","pvap":"1,79"},{"sqcand":"150001619824","n":"1455","nm":"JOSINALDO SOUSA","cc":"PTB","st":"Não eleito","dvt":"Válido","vap":"1433","pvap":"0,06"},{"sqcand":"150001643341","n":"1511","nm":"WALTER BRITO NETO","cc":"MDB","st":"Não eleito","dvt":"Válido","vap":"540","pvap":"0,02"},{"sqcand":"150001612087","n":"2010","nm":"RUBENS NASCIMENTO","cc":"PSC","st":"Suplente","dvt":"Válido","vap":"5249","pvap":"0,24"},{"sqcand":"150001729659","n":"2200","nm":"RICARDO MAIA","cc":"PL","st":"Suplente","dvt":"Válido","vap":"1391","pvap":"0,06"},{"sqcand":"150001718233","n":"2222","nm":"WELLINGTON ROBERTO","cc":"PL","st":"Eleito por média","dvt":"Válido","vap":"109067","pvap":"4,92"},{"sqcand":"150001718232","n":"2244","nm":"ROMEU LEMOS","cc":"PL","st":"Suplente","dvt":"Válido","vap":"1581","pvap":"0,07"},{"sqcand":"150001621684","n":"4022","nm":"RICARDO BARBOSA","cc":"PSB","st":"Suplente","dvt":"Válido","vap":"63777","pvap":"2,88"},{"sqcand":"150001603192","n":"4400","nm":"MARÍLIA DANTAS","cc":"UNIÃO","st":"Suplente","dvt":"Válido","vap":"2762","pvap":"0,12"},{"sqcand":"150001621392","n":"4555","nm":"PAULO GAYOSO","cc":"PSDB - Federação PSDB Cidadania (PSDB/CIDADANIA)","st":"Não eleito","dvt":"Válido","vap":"2908","pvap":"0,13"},{"sqcand":"150001643398","n":"7077","nm":"IRMÃO ROSIEL ALVES","cc":"AVANTE","st":"Não eleito","dvt":"Válido","vap":"482","pvap":"0,02"},{"sqcand":"150001620420","n":"7711","nm":"ENFERMEIRA DANI","cc":"SOLIDARIEDADE","st":"Não eleito","dvt":"Válido","vap":"754","pvap":"0,03"},{"sqcand":"150001620426","n":"7783","nm":"MILTON DANTUNES","cc":"SOLIDARIEDADE","st":"Não eleito","dvt":"Válido","vap":"1090","pvap":"0,05"},{"sqcand":"150001621683","n":"4004","nm":"FABIOLA REZENDE","cc":"PSB","st":"Suplente","dvt":"Válido","vap":"8236","pvap":"0,37"},{"sqcand":"150001621541","n":"5013","nm":"TARCIO TEIXEIRA","cc":"PSOL - Federação PSOL REDE (PSOL/REDE)","st":"Não eleito","dvt":"Válido","vap":"4806","pvap":"0,22"},{"sqcand":"150001612079","n":"2023","nm":"JAMERSON FERREIRA","cc":"PSC","st":"Suplente","dvt":"Válido","vap":"3344","pvap":"0,15"},{"sqcand":"150001603196","n":"4477","nm":"ANA NORONHA","cc":"UNIÃO","st":"Suplente","dvt":"Válido","vap":"3147","pvap":"0,14"},{"sqcand":"150001643400","n":"7070","nm":"ERICK TARGINO","cc":"AVANTE","st":"Não eleito","dvt":"Válido","vap":"307","pvap":"0,01"},{"sqcand":"150001643399","n":"7000","nm":"RODRIGO ROLIM","cc":"AVANTE","st":"Não eleito","dvt":"Válido","vap":"677","pvap":"0,03"},{"sqcand":"150001621536","n":"1800","nm":"POETA AZIEL LIMA","cc":"REDE - Federação PSOL REDE (PSOL/REDE)","st":"Não eleito","dvt":"Válido","vap":"828","pvap":"0,04"},{"sqcand":"150001619550","n":"1033","nm":"SILVIA DA PESCA","cc":"REPUBLICANOS","st":"Suplente","dvt":"Válido","vap":"17753","pvap":"0,80"},{"sqcand":"150001725482","n":"1257","nm":"IOLANDA AMERICO","cc":"PDT","st":"Não eleito","dvt":"Válido","vap":"137","pvap":"0,01"},{"sqcand":"150001619536","n":"6555","nm":"JONILDO CAVALCANTI","cc":"PC do B - Federação Brasil da Esperança - FE BRASIL (PT/PC do B/PV)","st":"Suplente","dvt":"Válido","vap":"3551","pvap":"0,16"},{"sqcand":"150001621544","n":"1870","nm":"MARCOS DINIZ","cc":"REDE - Federação PSOL REDE (PSOL/REDE)","st":"Não eleito","dvt":"Válido","vap":"593","pvap":"0,03"},{"sqcand":"150001619552","n":"1015","nm":"RANIERY PAULINO","cc":"REPUBLICANOS","st":"Suplente","dvt":"Válido","vap":"33550","pvap":"1,51"},{"sqcand":"150001638938","n":"1412","nm":"PASTOR JOSINO NETO","cc":"PTB","st":"Não eleito","dvt":"Válido","vap":"296","pvap":"0,01"},{"sqcand":"150001636668","n":"1999","nm":"JULIANNY","cc":"PODE","st":"Não eleito","dvt":"Válido","vap":"298","pvap":"0,01"},{"sqcand":"150001718398","n":"3678","nm":"RODRIGO NÓBREGA","cc":"AGIR","st":"Não eleito","dvt":"Válido","vap":"185","pvap":"0,01"},{"sqcand":"150001718396","n":"3635","nm":"NÍCIA CATÃO","cc":"AGIR","st":"Não eleito","dvt":"Válido","vap":"31","pvap":"0,00"},{"sqcand":"150001643331","n":"1533","nm":"AECIO CAVALCANTE","cc":"MDB","st":"Não eleito","dvt":"Válido","vap":"583","pvap":"0,03"},{"sqcand":"150001619538","n":"1312","nm":"LUIZ COUTO","cc":"PT - Federação Brasil da Esperança - FE BRASIL (PT/PC do B/PV)","st":"Eleito por QP","dvt":"Válido","vap":"54851","pvap":"2,47"},{"sqcand":"150001603198","n":"4422","nm":"ALEXANDRE DO SINDICATO","cc":"UNIÃO","st":"Suplente","dvt":"Válido","vap":"5441","pvap":"0,25"},{"sqcand":"150001619609","n":"2899","nm":"EMILLY COELHO","cc":"PRTB","st":"Não eleito","dvt":"Válido","vap":"1958","pvap":"0,09"},{"sqcand":"150001619541","n":"1300","nm":"PROFESSOR MÁRCIO CANIELLO","cc":"PT - Federação Brasil da Esperança - FE BRASIL (PT/PC do B/PV)","st":"Suplente","dvt":"Válido","vap":"2953","pvap":"0,13"},{"sqcand":"150001718126","n":"1237","nm":"GILVANDRO SILVA","cc":"PDT","st":"Não eleito","dvt":"Válido","vap":"263","pvap":"0,01"},{"sqcand":"150001643340","n":"1522","nm":"MILTON LÚCIO","cc":"MDB","st":"Não eleito","dvt":"Válido","vap":"2928","pvap":"0,13"},{"sqcand":"150001619556","n":"1055","nm":"ALYSSON GOMES","cc":"REPUBLICANOS","st":"Suplente","dvt":"Válido","vap":"3604","pvap":"0,16"},{"sqcand":"150001619825","n":"1456","nm":"LAERCIO BRAGA","cc":"PTB","st":"Não eleito","dvt":"Válido","vap":"797","pvap":"0,04"},{"sqcand":"150001621687","n":"4000","nm":"SANDRA MARROCOS","cc":"PSB","st":"Suplente","dvt":"Válido","vap":"7188","pvap":"0,32"},{"sqcand":"150001619823","n":"1411","nm":"CLENIER ALBUQUERQUE","cc":"PTB","st":"Não eleito","dvt":"Válido","vap":"233","pvap":"0,01"},{"sqcand":"150001612070","n":"1122","nm":"ELIZA","cc":"PP","st":"Suplente","dvt":"Válido","vap":"35838","pvap":"1,62"},{"sqcand":"150001619548","n":"1010","nm":"WILSON SANTIAGO","cc":"REPUBLICANOS","st":"Eleito por média","dvt":"Válido","vap":"84407","pvap":"3,81"},{"sqcand":"150001643338","n":"1500","nm":"GOBIRA","cc":"MDB","st":"Não eleito","dvt":"Válido","vap":"2383","pvap":"0,11"},{"sqcand":"150001636669","n":"1919","nm":"MISSINHO DO BODE","cc":"PODE","st":"Não eleito","dvt":"Válido","vap":"335","pvap":"0,02"},{"sqcand":"150001718231","n":"2233","nm":"RAPHAEL TCHUTCHUCA","cc":"PL","st":"Suplente","dvt":"Válido","vap":"3056","pvap":"0,14"},{"sqcand":"150001620417","n":"7700","nm":"PEDRO CHAVES","cc":"SOLIDARIEDADE","st":"Não eleito","dvt":"Válido","vap":"947","pvap":"0,04"},{"sqcand":"150001621677","n":"4077","nm":"MARCOS CAVALCANTI","cc":"PSB","st":"Suplente","dvt":"Válido","vap":"948","pvap":"0,04"},{"sqcand":"150001619553","n":"1001","nm":"SUANA MELO","cc":"REPUBLICANOS","st":"Suplente","dvt":"Válido","vap":"1904","pvap":"0,09"},{"sqcand":"150001619616","n":"2829","nm":"ATALIBA O  ARRUDA","cc":"PRTB","st":"Não eleito","dvt":"Válido","vap":"934","pvap":"0,04"},{"sqcand":"150001621547","n":"1890","nm":"PROFESSOR CATIER","cc":"REDE - Federação PSOL REDE (PSOL/REDE)","st":"Não eleito","dvt":"Válido","vap":"659","pvap":"0,03"},{"sqcand":"150001619551","n":"1012","nm":"MARMUTHE","cc":"REPUBLICANOS","st":"Suplente","dvt":"Válido","vap":"11469","pvap":"0,52"},{"sqcand":"150001603203","n":"4411","nm":"FERNANDINHA","cc":"UNIÃO","st":"Suplente","dvt":"Válido","vap":"28241","pvap":"1,27"},{"sqcand":"150001619833","n":"1414","nm":"DEDÉ SALES","cc":"PTB","st":"Não eleito","dvt":"Válido","vap":"2814","pvap":"0,13"},{"sqcand":"150001718401","n":"3614","nm":"WILMA SANTOS","cc":"AGIR","st":"Não eleito","dvt":"Válido","vap":"3","pvap":"0,01"},{"sqcand":"150001718228","n":"2223","nm":"CANTORA MUNIQUE MARINHO","cc":"PL","st":"Suplente","dvt":"Válido","vap":"10284","pvap":"0,46"},{"sqcand":"150001718124","n":"1234","nm":"NILDO LACERDA","cc":"PDT","st":"Não eleito","dvt":"Válido","vap":"2531","pvap":"0,11"},{"sqcand":"150001732873","n":"1544","nm":"ELANDIA ABRANTES","cc":"MDB","st":"Não eleito","dvt":"Válido","vap":"458","pvap":"0,02"},{"sqcand":"150001737743","n":"1211","nm":"VIVI LINS ENFERMEIRA","cc":"PDT","st":"Não eleito","dvt":"Válido","vap":"435","pvap":"0,02"},{"sqcand":"150001718471","n":"5113","nm":"HELIO SERRANO","cc":"PATRIOTA","st":"Não eleito","dvt":"Válido","vap":"272","pvap":"0,01"},{"sqcand":"150001718475","n":"5112","nm":"ROBERTO LIMA","cc":"PATRIOTA","st":"Não eleito","dvt":"Válido","vap":"208","pvap":"0,01"},{"sqcand":"150001643335","n":"1599","nm":"RAFAELLA BRONZEADO","cc":"MDB","st":"Não eleito","dvt":"Válido","vap":"411","pvap":"0,02"},{"sqcand":"150001603201","n":"4444","nm":"JULIAN LEMOS","cc":"UNIÃO","st":"Suplente","dvt":"Válido","vap":"36530","pvap":"1,65"},{"sqcand":"150001718229","n":"2225","nm":"ARTUR CUNHA LIMA FILHO","cc":"PL","st":"Suplente","dvt":"Válido","vap":"1612","pvap":"0,07"},{"sqcand":"150001619542","n":"6513","nm":"MYRA MARINHO","cc":"PC do B - Federação Brasil da Esperança - FE BRASIL (PT/PC do B/PV)","st":"Suplente","dvt":"Válido","vap":"227","pvap":"0,01"},{"sqcand":"150001718121","n":"1222","nm":"MAYANNE BASTOS","cc":"PDT","st":"Não eleito","dvt":"Válido","vap":"688","pvap":"0,03"},{"sqcand":"150001619535","n":"4343","nm":"JOYCE CALIXTO","cc":"PV - Federação Brasil da Esperança - FE BRASIL (PT/PC do B/PV)","st":"Suplente","dvt":"Válido","vap":"480","pvap":"0,02"},{"sqcand":"150001612088","n":"2022","nm":"PATRICK DORNELES","cc":"PSC","st":"Suplente","dvt":"Válido","vap":"5544","pvap":"0,25"},{"sqcand":"150001612085","n":"2077","nm":"MARINA VENÂNCIO","cc":"PSC","st":"Suplente","dvt":"Válido","vap":"4513","pvap":"0,20"},{"sqcand":"150001718238","n":"2238","nm":"ILMARA MORAIS","cc":"PL","st":"Suplente","dvt":"Válido","vap":"5226","pvap":"0,24"},{"sqcand":"150001621682","n":"4013","nm":"RAFAELA CAMARAENSE","cc":"PSB","st":"Suplente","dvt":"Válido","vap":"43477","pvap":"1,96"},{"sqcand":"150001643336","n":"1513","nm":"ALEXANDRE ALMEIDA","cc":"MDB","st":"Não eleito","dvt":"Válido","vap":"8009","pvap":"0,36"},{"sqcand":"150001723467","n":"3544","nm":"SILVA NETO","cc":"PMB","st":"Não eleito","dvt":"Válido","vap":"306","pvap":"0,01"},{"sqcand":"150001718130","n":"2021","nm":"DRA FRANCIMAR RAMOS","cc":"PSC","st":"Suplente","dvt":"Válido","vap":"1706","pvap":"0,08"},{"sqcand":"150001619531","n":"1330","nm":"ROSILDA SOARES","cc":"PT - Federação Brasil da Esperança - FE BRASIL (PT/PC do B/PV)","st":"Suplente","dvt":"Válido","vap":"827","pvap":"0,04"},{"sqcand":"150001615549","n":"9090","nm":"NEGATIVO","cc":"PROS","st":"Não eleito","dvt":"Anulado sub judice","vap":"298","pvap":"0,01"},{"sqcand":"150001621614","n":"2727","nm":"DANILO ILTON","cc":"DC","st":"Não eleito","dvt":"Anulado sub judice","vap":"419","pvap":"0,02"},{"sqcand":"150001737750","n":"3550","nm":"SAULO PORTO LAMPIÃO","cc":"PMB","st":"Não eleito","dvt":"Anulado sub judice","vap":"59","pvap":"0,00"},{"sqcand":"150001718481","n":"5100","nm":"GEISI PATRIOTA","cc":"PATRIOTA","st":"Não eleito","dvt":"Anulado sub judice","vap":"227","pvap":"0,01"},{"sqcand":"150001603200","n":"4410","nm":"DOUGLAS LUCENA","cc":"UNIÃO","st":"Não eleito","dvt":"Anulado sub judice","vap":"6586","pvap":"0,30"},{"sqcand":"150001718479","n":"5131","nm":"KATHELLEM DE JESUS","cc":"PATRIOTA","st":"Não eleito","dvt":"Anulado sub judice","vap":"165","pvap":"0,01"},{"sqcand":"150001615545","n":"9010","nm":"DIANA XAVIER","cc":"PROS","st":"Não eleito","dvt":"Anulado sub judice","vap":"172","pvap":"0,01"},{"sqcand":"150001603194","n":"4433","nm":"JACÓ MACIEL","cc":"UNIÃO","st":"Não eleito","dvt":"Anulado sub judice","vap":"17145","pvap":"0,77"},{"sqcand":"150001718472","n":"5151","nm":"JESSYCA LUANA","cc":"PATRIOTA","st":"Não eleito","dvt":"Anulado sub judice","vap":"90","pvap":"0,00"},{"sqcand":"150001612089","n":"2030","nm":"RUY CARNEIRO","cc":"PSC","st":"Eleito por média","dvt":"Válido","vap":"102531","pvap":"4,62"},{"sqcand":"150001643337","n":"1515","nm":"MIKIKA LEITÃO","cc":"MDB","st":"Não eleito","dvt":"Válido","vap":"19362","pvap":"0,87"},{"sqcand":"150001718230","n":"2255","nm":"IRMÃ RUTE NERI","cc":"PL","st":"Suplente","dvt":"Válido","vap":"1551","pvap":"0,07"},{"sqcand":"150001620419","n":"7707","nm":"NICOLA","cc":"SOLIDARIEDADE","st":"Não eleito","dvt":"Válido","vap":"924","pvap":"0,04"},{"sqcand":"150001612069","n":"1155","nm":"GUGA OLIVEIRA","cc":"PP","st":"Suplente","dvt":"Válido","vap":"14353","pvap":"0,65"},{"sqcand":"150001620425","n":"7777","nm":"GALEGA DO POVO","cc":"SOLIDARIEDADE","st":"Não eleito","dvt":"Válido","vap":"2807","pvap":"0,13"},{"sqcand":"150001718236","n":"2245","nm":"WILSINHO","cc":"PL","st":"Suplente","dvt":"Válido","vap":"3985","pvap":"0,18"},{"sqcand":"150001726525","n":"7010","nm":"KEILLA FERNANDES","cc":"AVANTE","st":"Não eleito","dvt":"Válido","vap":"136","pvap":"0,01"},{"sqcand":"150001619607","n":"2810","nm":"MORGANA MACENA","cc":"PRTB","st":"Não eleito","dvt":"Válido","vap":"1457","pvap":"0,07"},{"sqcand":"150001718399","n":"3613","nm":"PROFESSOR MONTENEGRO","cc":"AGIR","st":"Não eleito","dvt":"Válido","vap":"69","pvap":"0,00"},{"sqcand":"150001619549","n":"1088","nm":"GAROTINHO","cc":"REPUBLICANOS","st":"Suplente","dvt":"Válido","vap":"1544","pvap":"0,07"},{"sqcand":"150001723466","n":"3570","nm":"PEDRO ABELHINHA PONTE ALCÂNTAR","cc":"PMB","st":"Não eleito","dvt":"Válido","vap":"33","pvap":"0,00"},{"sqcand":"150001619831","n":"1422","nm":"SANDRO GALVÃO","cc":"PTB","st":"Não eleito","dvt":"Válido","vap":"455","pvap":"0,02"},{"sqcand":"150001619610","n":"2801","nm":"JOELNA FIGUEIREDO","cc":"PRTB","st":"Não eleito","dvt":"Válido","vap":"370","pvap":"0,02"},{"sqcand":"150001621678","n":"4099","nm":"ADONES","cc":"PSB","st":"Suplente","dvt":"Válido","vap":"2962","pvap":"0,13"},{"sqcand":"150001718400","n":"3636","nm":"PROFESSORA ANDRÉIA DO RÊGO","cc":"AGIR","st":"Não eleito","dvt":"Válido","vap":"89","pvap":"0,00"},{"sqcand":"150001718474","n":"5130","nm":"SEVERINO XELECO","cc":"PATRIOTA","st":"Não eleito","dvt":"Válido","vap":"287","pvap":"0,01"},{"sqcand":"150001643334","n":"1566","nm":"DEDA CLAUDINO","cc":"MDB","st":"Não eleito","dvt":"Válido","vap":"6121","pvap":"0,28"},{"sqcand":"150001612080","n":"2020","nm":"LÉO GADELHA","cc":"PSC","st":"Suplente","dvt":"Válido","vap":"65573","pvap":"2,96"},{"sqcand":"150001621396","n":"4577","nm":"VIEGAS","cc":"PSDB - Federação PSDB Cidadania (PSDB/CIDADANIA)","st":"Não eleito","dvt":"Válido","vap":"528","pvap":"0,02"},{"sqcand":"150001603199","n":"4499","nm":"MAJOR NETO","cc":"UNIÃO","st":"Suplente","dvt":"Válido","vap":"4367","pvap":"0,20"},{"sqcand":"150001603193","n":"4455","nm":"CAROL GOMES","cc":"UNIÃO","st":"Suplente","dvt":"Válido","vap":"22417","pvap":"1,01"},{"sqcand":"150001718478","n":"5111","nm":"DR ANTONIO CARLOS","cc":"PATRIOTA","st":"Não eleito","dvt":"Válido","vap":"353","pvap":"0,02"},{"sqcand":"150001621395","n":"4510","nm":"LUANNA MOURA","cc":"PSDB - Federação PSDB Cidadania (PSDB/CIDADANIA)","st":"Não eleito","dvt":"Válido","vap":"668","pvap":"0,03"},{"sqcand":"150001619530","n":"1313","nm":"ESTELA BEZERRA","cc":"PT - Federação Brasil da Esperança - FE BRASIL (PT/PC do B/PV)","st":"Suplente","dvt":"Válido","vap":"44788","pvap":"2,02"},{"sqcand":"150001621676","n":"4033","nm":"MANOEL ISIDRO","cc":"PSB","st":"Suplente","dvt":"Válido","vap":"3435","pvap":"0,15"},{"sqcand":"150001620421","n":"7733","nm":"MAURÍCIO JOSÉ","cc":"SOLIDARIEDADE","st":"Não eleito","dvt":"Válido","vap":"27","pvap":"0,00"},{"sqcand":"150001718125","n":"1212","nm":"FERNANDO MEDEIROS","cc":"PDT","st":"Não eleito","dvt":"Válido","vap":"1268","pvap":"0,06"},{"sqcand":"150001619829","n":"1441","nm":"DANIELLE MAGLIANO","cc":"PTB","st":"Não eleito","dvt":"Válido","vap":"281","pvap":"0,01"},{"sqcand":"150001612071","n":"1101","nm":"HELENA HOLANDA","cc":"PP","st":"Suplente","dvt":"Válido","vap":"5761","pvap":"0,26"},{"sqcand":"150001620422","n":"7722","nm":"RINALDO MARANHÃO","cc":"SOLIDARIEDADE","st":"Não eleito","dvt":"Válido","vap":"2788","pvap":"0,13"},{"sqcand":"150001621679","n":"4040","nm":"GERVASIO MAIA","cc":"PSB","st":"Eleito por QP","dvt":"Válido","vap":"69405","pvap":"3,13"},{"sqcand":"150001612066","n":"1166","nm":"ALINE","cc":"PP","st":"Suplente","dvt":"Válido","vap":"966","pvap":"0,04"},{"sqcand":"150001619605","n":"2882","nm":"PASTOR JADER MEDEIROS","cc":"PRTB","st":"Não eleito","dvt":"Válido","vap":"4003","pvap":"0,18"},{"sqcand":"150001619533","n":"1333","nm":"LUCÉLIO CARTAXO","cc":"PT - Federação Brasil da Esperança - FE BRASIL (PT/PC do B/PV)","st":"Suplente","dvt":"Válido","vap":"14723","pvap":"0,66"},{"sqcand":"150001621538","n":"1818","nm":"PROFESSOR EUDO JANSEN","cc":"REDE - Federação PSOL REDE (PSOL/REDE)","st":"Não eleito","dvt":"Válido","vap":"416","pvap":"0,02"},{"sqcand":"150001620415","n":"7744","nm":"MALBA DO POVO","cc":"SOLIDARIEDADE","st":"Não eleito","dvt":"Válido","vap":"1378","pvap":"0,06"},{"sqcand":"150001718237","n":"2288","nm":"RAQUEL SANTANA","cc":"PL","st":"Suplente","dvt":"Válido","vap":"1906","pvap":"0,09"},{"sqcand":"150001612081","n":"2000","nm":"PÂMELA BÓRIO","cc":"PSC","st":"Suplente","dvt":"Válido","vap":"1373","pvap":"0,06"},{"sqcand":"150001643402","n":"7002","nm":"CAMILA DELFINO","cc":"AVANTE","st":"Não eleito","dvt":"Válido","vap":"47","pvap":"0,00"},{"sqcand":"150001621548","n":"1888","nm":"LANA DANTAS","cc":"REDE - Federação PSOL REDE (PSOL/REDE)","st":"Não eleito","dvt":"Válido","vap":"5710","pvap":"0,26"},{"sqcand":"150001621686","n":"4044","nm":"DR GERALDO MEDEIROS","cc":"PSB","st":"Suplente","dvt":"Válido","vap":"19293","pvap":"0,87"},{"sqcand":"150001612065","n":"1111","nm":"AGUINALDO RIBEIRO","cc":"PP","st":"Eleito por QP","dvt":"Válido","vap":"135001","pvap":"6,09"},{"sqcand":"150001621537","n":"1840","nm":"DALMO","cc":"REDE - Federação PSOL REDE (PSOL/REDE)","st":"Não eleito","dvt":"Válido","vap":"172","pvap":"0,01"},{"sqcand":"150001619827","n":"1415","nm":"LIA LOURENÇO","cc":"PTB","st":"Não eleito","dvt":"Válido","vap":"146","pvap":"0,01"},{"sqcand":"150001619612","n":"2878","nm":"RICARDO ALEXANDRE","cc":"PRTB","st":"Não eleito","dvt":"Válido","vap":"95","pvap":"0,00"},{"sqcand":"150001643403","n":"7012","nm":"HOMERO SÁTIRO","cc":"AVANTE","st":"Não eleito","dvt":"Válido","vap":"346","pvap":"0,02"},{"sqcand":"150001621681","n":"4012","nm":"HERON CID","cc":"PSB","st":"Suplente","dvt":"Válido","vap":"8544","pvap":"0,39"},{"sqcand":"150001619555","n":"1077","nm":"VALDIR TRINDADE","cc":"REPUBLICANOS","st":"Suplente","dvt":"Válido","vap":"27172","pvap":"1,23"},{"sqcand":"150001620418","n":"7778","nm":"PEDRO JR BARATA","cc":"SOLIDARIEDADE","st":"Não eleito","dvt":"Válido","vap":"450","pvap":"0,02"},{"sqcand":"150001619606","n":"2813","nm":"MOISÉS GIRRÔ","cc":"PRTB","st":"Não eleito","dvt":"Válido","vap":"311","pvap":"0,01"},{"sqcand":"150001718477","n":"5177","nm":"VAGNER LACERDA","cc":"PATRIOTA","st":"Não eleito","dvt":"Válido","vap":"330","pvap":"0,01"},{"sqcand":"150001621545","n":"1881","nm":"ARAÚJO","cc":"REDE - Federação PSOL REDE (PSOL/REDE)","st":"Não eleito","dvt":"Válido","vap":"228","pvap":"0,01"},{"sqcand":"150001612074","n":"1144","nm":"MERSINHO LUCENA","cc":"PP","st":"Eleito por média","dvt":"Válido","vap":"114818","pvap":"5,18"},{"sqcand":"150001643401","n":"7040","nm":"JOSUÉ SOUZA","cc":"AVANTE","st":"Não eleito","dvt":"Válido","vap":"1872","pvap":"0,08"},{"sqcand":"150001725481","n":"2055","nm":"PROF ASSIS PINHEIRO","cc":"PSC","st":"Suplente","dvt":"Válido","vap":"327","pvap":"0,01"},{"sqcand":"150001621685","n":"4008","nm":"ZOIAO DA PARAIBA","cc":"PSB","st":"Suplente","dvt":"Válido","vap":"296","pvap":"0,01"},{"sqcand":"150001612072","n":"1177","nm":"DR° HILTON SOUTO MAIOR","cc":"PP","st":"Suplente","dvt":"Válido","vap":"8156","pvap":"0,37"},{"sqcand":"150001619832","n":"1410","nm":"MÉRCIO FRANKLIN","cc":"PTB","st":"Não eleito","dvt":"Válido","vap":"872","pvap":"0,04"},{"sqcand":"150001621615","n":"2787","nm":"JENIFFER FELINTRO","cc":"DC","st":"Não eleito","dvt":"Válido","vap":"46","pvap":"0,00"},{"sqcand":"150001718239","n":"2210","nm":"CABO GILBERTO SILVA","cc":"PL","st":"Eleito por QP","dvt":"Válido","vap":"126876","pvap":"5,72"},{"sqcand":"150001609926","n":"8080","nm":"JOZIVAN ANTERO","cc":"UP","st":"Não eleito","dvt":"Válido","vap":"1337","pvap":"0,06"},{"sqcand":"150001612082","n":"2014","nm":"DANIELA CATURITÉ","cc":"PSC","st":"Suplente","dvt":"Válido","vap":"3210","pvap":"0,14"},{"sqcand":"150001728054","n":"4066","nm":"TITA","cc":"PSB","st":"Suplente","dvt":"Válido","vap":"100","pvap":"0,00"},{"sqcand":"150001643404","n":"7022","nm":"VITAL FARIAS","cc":"AVANTE","st":"Não eleito","dvt":"Válido","vap":"205","pvap":"0,01"},{"sqcand":"150001718473","n":"5122","nm":"THALITA LOPES","cc":"PATRIOTA","st":"Não eleito","dvt":"Anulado sub judice","vap":"166","pvap":"0,01"},{"sqcand":"150001621680","n":"4010","nm":"HERMANCITA","cc":"PSB","st":"Não eleito","dvt":"Anulado sub judice","vap":"1420","pvap":"0,06"},{"sqcand":"150001737746","n":"3560","nm":"JOTA FERREIRA","cc":"PMB","st":"Não eleito","dvt":"Anulado sub judice","vap":"129","pvap":"0,01"},{"sqcand":"150001737747","n":"3522","nm":"ROSE EMANUELE","cc":"PMB","st":"Não eleito","dvt":"Anulado sub judice","vap":"56","pvap":"0,00"},{"sqcand":"150001718404","n":"3631","nm":"PROFESSOR DR. RAFAEL","cc":"AGIR","st":"Não eleito","dvt":"Anulado sub judice","vap":"246","pvap":"0,01"},{"sqcand":"150001718249","n":"2900","nm":"VALTEMBERG ALVES DE ALMEIDA","cc":"PCO","st":"Não eleito","dvt":"Anulado sub judice","vap":"48","pvap":"0,00"},{"sqcand":"150001737751","n":"3590","nm":"ADAILTO BARROS","cc":"PMB","st":"Não eleito","dvt":"Anulado sub judice","vap":"43","pvap":"0,00"},{"sqcand":"150001718250","n":"2901","nm":"IOLANDA ALVES FEITOZA","cc":"PCO","st":"Não eleito","dvt":"Anulado sub judice","vap":"6","pvap":"0,01"},{"sqcand":"150001737748","n":"3555","nm":"EDSON ALVES","cc":"PMB","st":"Não eleito","dvt":"Anulado sub judice","vap":"55","pvap":"0,00"},{"sqcand":"150001718248","n":"2929","nm":"JOSÉ MARCOS","cc":"PCO","st":"Não eleito","dvt":"Anulado sub judice","vap":"102","pvap":"0,00"},{"sqcand":"150001723470","n":"3567","nm":"MANUELA SANTANA","cc":"PMB","st":"Não eleito","dvt":"Válido","vap":"35","pvap":"0,00"},{"sqcand":"150001619534","n":"4313","nm":"LUIZ MIGUEL","cc":"PV - Federação Brasil da Esperança - FE BRASIL (PT/PC do B/PV)","st":"Suplente","dvt":"Válido","vap":"497","pvap":"0,02"},{"sqcand":"150001723465","n":"3512","nm":"MARILIA GOMES","cc":"PMB","st":"Não eleito","dvt":"Válido","vap":"77","pvap":"0,00"},{"sqcand":"150001619614","n":"2888","nm":"PAULO FERREIRA","cc":"PRTB","st":"Não eleito","dvt":"Válido","vap":"4057","pvap":"0,18"},{"sqcand":"150001612068","n":"1121","nm":"BARATA","cc":"PP","st":"Suplente","dvt":"Válido","vap":"159","pvap":"0,01"},{"sqcand":"150001619828","n":"1400","nm":"CRECIA GALEGA DO RG","cc":"PTB","st":"Não eleito","dvt":"Válido","vap":"883","pvap":"0,04"},{"sqcand":"150001603195","n":"4412","nm":"DR. DAMIÃO","cc":"UNIÃO","st":"Eleito por QP","dvt":"Válido","vap":"64023","pvap":"2,89"},{"sqcand":"150001619554","n":"1000","nm":"DRA TATIANA MEDEIROS","cc":"REPUBLICANOS","st":"Suplente","dvt":"Válido","vap":"9784","pvap":"0,44"},{"sqcand":"150001619826","n":"1477","nm":"CARLOS DORNELAS","cc":"PTB","st":"Não eleito","dvt":"Válido","vap":"457","pvap":"0,02"},{"sqcand":"150001621542","n":"5050","nm":"BRUNA SANTOS","cc":"PSOL - Federação PSOL REDE (PSOL/REDE)","st":"Não eleito","dvt":"Válido","vap":"613","pvap":"0,03"},{"sqcand":"150001612083","n":"2088","nm":"DRA JOELMA","cc":"PSC","st":"Suplente","dvt":"Válido","vap":"2598","pvap":"0,12"},{"sqcand":"150001603202","n":"4488","nm":"MISSIONÁRIA JANE","cc":"UNIÃO","st":"Suplente","dvt":"Válido","vap":"501","pvap":"0,02"},{"sqcand":"150001643339","n":"1577","nm":"DRA MÁRCIA RIBEIRO","cc":"MDB","st":"Não eleito","dvt":"Válido","vap":"394","pvap":"0,02"},{"sqcand":"150001619544","n":"1044","nm":"MURILO GALDINO","cc":"REPUBLICANOS","st":"Eleito por QP","dvt":"Válido","vap":"112891","pvap":"5,09"},{"sqcand":"150001620423","n":"7710","nm":"PASTORA RAMINHA","cc":"SOLIDARIEDADE","st":"Não eleito","dvt":"Válido","vap":"236","pvap":"0,01"},{"sqcand":"150001718476","n":"5134","nm":"SILVIO SOARES","cc":"PATRIOTA","st":"Não eleito","dvt":"Válido","vap":"234","pvap":"0,01"},{"sqcand":"150001621540","n":"1813","nm":"PRETA","cc":"REDE - Federação PSOL REDE (PSOL/REDE)","st":"Não eleito","dvt":"Válido","vap":"1062","pvap":"0,05"},{"sqcand":"150001718402","n":"3610","nm":"JOSEPH MEDEIROS","cc":"AGIR","st":"Não eleito","dvt":"Válido","vap":"41","pvap":"0,00"},{"sqcand":"150001619615","n":"2800","nm":"PROFESSOR JOÃO ALBERTO","cc":"PRTB","st":"Não eleito","dvt":"Válido","vap":"2567","pvap":"0,12"},{"sqcand":"150001718128","n":"1200","nm":"MIMINHO","cc":"PDT","st":"Não eleito","dvt":"Válido","vap":"339","pvap":"0,02"},{"sqcand":"150001612084","n":"2033","nm":"PINTADO","cc":"PSC","st":"Suplente","dvt":"Válido","vap":"1333","pvap":"0,06"},{"sqcand":"150001621394","n":"4588","nm":"CIBELLE MANGUEIRA","cc":"PSDB - Federação PSDB Cidadania (PSDB/CIDADANIA)","st":"Não eleito","dvt":"Válido","vap":"550","pvap":"0,02"},{"sqcand":"150001643397","n":"7001","nm":"LETICIA","cc":"AVANTE","st":"Não eleito","dvt":"Válido","vap":"416","pvap":"0,02"},{"sqcand":"150001718397","n":"3616","nm":"ELANE AGRA","cc":"AGIR","st":"Não eleito","dvt":"Válido","vap":"22","pvap":"0,01"},{"sqcand":"150001619537","n":"1355","nm":"HELOÍSA DA COLETIVA NOSSA VOZ","cc":"PT - Federação Brasil da Esperança - FE BRASIL (PT/PC do B/PV)","st":"Suplente","dvt":"Válido","vap":"4981","pvap":"0,22"},{"sqcand":"150001603197","n":"4424","nm":"RAFAFÁ","cc":"UNIÃO","st":"Suplente","dvt":"Válido","vap":"8701","pvap":"0,39"},{"sqcand":"150001620424","n":"7788","nm":"MAZÉ EXCURSÕES","cc":"SOLIDARIEDADE","st":"Não eleito","dvt":"Válido","vap":"404","pvap":"0,02"},{"sqcand":"150001619830","n":"1444","nm":"MARTINS O GARI POETA","cc":"PTB","st":"Não eleito","dvt":"Válido","vap":"920","pvap":"0,04"},{"sqcand":"150001643342","n":"1567","nm":"AMANDA CSI","cc":"MDB","st":"Não eleito","dvt":"Válido","vap":"12085","pvap":"0,54"},{"sqcand":"150001619547","n":"1099","nm":"JUNIOR DRZINHO","cc":"REPUBLICANOS","st":"Suplente","dvt":"Válido","vap":"4762","pvap":"0,21"},{"sqcand":"150001612086","n":"2011","nm":"ROMERO RODRIGUES","cc":"PSC","st":"Eleito por QP","dvt":"Válido","vap":"114573","pvap":"5,17"},{"sqcand":"150001609925","n":"8000","nm":"RADAMÉS","cc":"UP","st":"Não eleito","dvt":"Válido","vap":"698","pvap":"0,03"},{"sqcand":"150001619604","n":"2822","nm":"CABO LÚCIA","cc":"PRTB","st":"Não eleito","dvt":"Válido","vap":"110","pvap":"0,00"},{"sqcand":"150001612067","n":"1100","nm":"GUSTAVO RAMOS","cc":"PP","st":"Suplente","dvt":"Válido","vap":"913","pvap":"0,04"},{"sqcand":"150001620416","n":"7712","nm":"RADA CARLOS","cc":"SOLIDARIEDADE","st":"Não eleito","dvt":"Válido","vap":"394","pvap":"0,02"},{"sqcand":"150001621543","n":"1811","nm":"CÉLIA DAS MULHERES","cc":"REDE - Federação PSOL REDE (PSOL/REDE)","st":"Não eleito","dvt":"Válido","vap":"300","pvap":"0,01"},{"sqcand":"150001636670","n":"1900","nm":"CARLOS GALEGO","cc":"PODE","st":"Não eleito","dvt":"Válido","vap":"562","pvap":"0,03"},{"sqcand":"150001609927","n":"8008","nm":"VITÓRIA PODER DELAS","cc":"UP","st":"Não eleito","dvt":"Válido","vap":"1374","pvap":"0,06"},{"sqcand":"150001718235","n":"2211","nm":"POLICIAL CAIO","cc":"PL","st":"Suplente","dvt":"Válido","vap":"6850","pvap":"0,31"},{"sqcand":"150001619611","n":"2872","nm":"ADONAI","cc":"PRTB","st":"Não eleito","dvt":"Válido","vap":"74","pvap":"0,00"},{"sqcand":"150001643332","n":"1510","nm":"ANDERSON ALMEIDA - PILA","cc":"MDB","st":"Não eleito","dvt":"Válido","vap":"6012","pvap":"0,27"},{"sqcand":"150001619545","n":"1011","nm":"HUGO MOTTA","cc":"REPUBLICANOS","st":"Eleito por QP","dvt":"Válido","vap":"158171","pvap":"7,13"},{"sqcand":"150001621393","n":"4545","nm":"ELENILDO GOMES","cc":"PSDB - Federação PSDB Cidadania (PSDB/CIDADANIA)","st":"Não eleito","dvt":"Válido","vap":"562","pvap":"0,03"},{"sqcand":"150001643333","n":"1555","nm":"BENJAMIN MARANHÃO","cc":"MDB","st":"Não eleito","dvt":"Válido","vap":"7163","pvap":"0,32"},{"sqcand":"150001621546","n":"1899","nm":"BOCA","cc":"REDE - Federação PSOL REDE (PSOL/REDE)","st":"Não eleito","dvt":"Válido","vap":"347","pvap":"0,02"},{"sqcand":"150001603191","n":"4456","nm":"GENILSON LUCENYAH","cc":"UNIÃO","st":"Suplente","dvt":"Válido","vap":"4425","pvap":"0,20"},{"sqcand":"150001615548","n":"9000","nm":"ADRIANO FONSECA","cc":"PROS","st":"Não eleito","dvt":"Válido","vap":"305","pvap":"0,01"},{"sqcand":"150001621539","n":"1819","nm":"MARCELA","cc":"REDE - Federação PSOL REDE (PSOL/REDE)","st":"Não eleito","dvt":"Válido","vap":"402","pvap":"0,02"},{"sqcand":"150001612076","n":"1112","nm":"NARA MARQUES","cc":"PP","st":"Suplente","dvt":"Válido","vap":"2434","pvap":"0,11"}]}